RegimeDetect/Happynow.py
RegimeDetect/__init__.py
RegimeDetect/calculateTHD.py
RegimeDetect-0.1.2.dist-info/LICENSE
RegimeDetect-0.1.2.dist-info/METADATA
RegimeDetect-0.1.2.dist-info/WHEEL
RegimeDetect-0.1.2.dist-info/top_level.txt
RegimeDetect-0.1.2.dist-info/RECORD
