Metadata-Version: 2.1
Name: RegimeDetect
Version: 0.1.2
Summary: detect the rigime shift of time series data
Home-page: https://github.com/WencaiZheng
Author: Noven Zheng
Author-email: wz1298@nyu.edu
License: MIT License
Keywords: regime shift detection
Platform: any
